backend/__init__.py
backend/server.py
backend/utils.py
backend/websocket_manager.py
backend/report_type/__init__.py
backend/report_type/basic_report/__init__.py
backend/report_type/basic_report/basic_report.py
backend/report_type/detailed_report/__init__.py
backend/report_type/detailed_report/detailed_report.py
gpt_researcher/__init__.py
gpt_researcher/config/__init__.py
gpt_researcher/config/config.py
gpt_researcher/context/__init__.py
gpt_researcher/context/compression.py
gpt_researcher/context/retriever.py
gpt_researcher/document/__init__.py
gpt_researcher/document/document.py
gpt_researcher/llm_provider/__init__.py
gpt_researcher/llm_provider/anthropic/__init__.py
gpt_researcher/llm_provider/anthropic/anthropic.py
gpt_researcher/llm_provider/azureopenai/__init__.py
gpt_researcher/llm_provider/azureopenai/azureopenai.py
gpt_researcher/llm_provider/generic/__init__.py
gpt_researcher/llm_provider/generic/base.py
gpt_researcher/llm_provider/google/__init__.py
gpt_researcher/llm_provider/google/google.py
gpt_researcher/llm_provider/groq/__init__.py
gpt_researcher/llm_provider/groq/groq.py
gpt_researcher/llm_provider/huggingface/__init__.py
gpt_researcher/llm_provider/huggingface/huggingface.py
gpt_researcher/llm_provider/mistral/__init__.py
gpt_researcher/llm_provider/mistral/mistral.py
gpt_researcher/llm_provider/ollama/__init__.py
gpt_researcher/llm_provider/ollama/ollama.py
gpt_researcher/llm_provider/openai/__init__.py
gpt_researcher/llm_provider/openai/openai.py
gpt_researcher/llm_provider/together/__init__.py
gpt_researcher/llm_provider/together/together.py
gpt_researcher/master/__init__.py
gpt_researcher/master/actions.py
gpt_researcher/master/agent.py
gpt_researcher/master/prompts.py
gpt_researcher/memory/__init__.py
gpt_researcher/memory/embeddings.py
gpt_researcher/retrievers/__init__.py
gpt_researcher/retrievers/bing/__init__.py
gpt_researcher/retrievers/bing/bing.py
gpt_researcher/retrievers/duckduckgo/__init__.py
gpt_researcher_ian-0.6.11.dist-info/LICENSE
gpt_researcher_ian-0.6.11.dist-info/METADATA
gpt_researcher_ian-0.6.11.dist-info/WHEEL
gpt_researcher_ian-0.6.11.dist-info/top_level.txt
gpt_researcher_ian-0.6.11.dist-info/RECORD
